{"traceID": "035db1fec5a771dd", "spans": [{"traceID": "035db1fec5a771dd", "spanID": "ff10cf54abba4050", "flags": 1, "operationName": "url_mongo_insert_client", "references": [{"refType": "CHILD_OF", "traceID": "035db1fec5a771dd", "spanID": "4cb27aad49fd9875"}], "startTime": 1666132434488489, "duration": 335, "tags": [{"key": "internal.span.format", "type": "string", "value": "proto"}], "logs": [], "processID": "p1", "warnings": null}, {"traceID": "035db1fec5a771dd", "spanID": "4cb27aad49fd9875", "flags": 1, "operationName": "compose_urls_server", "references": [{"refType": "CHILD_OF", "traceID": "035db1fec5a771dd", "spanID": "834bf3ff30f3a76a"}], "startTime": 1666132434488434, "duration": 434, "tags": [{"key": "internal.span.format", "type": "string", "value": "proto"}], "logs": [], "processID": "p1", "warnings": null}, {"traceID": "035db1fec5a771dd", "spanID": "f2cf15bccc746087", "flags": 1, "operationName": "compose_unique_id_client", "references": [{"refType": "CHILD_OF", "traceID": "035db1fec5a771dd", "spanID": "de8f831afe09a226"}], "startTime": 1666132434487702, "duration": 134, "tags": [{"key": "internal.span.format", "type": "string", "value": "proto"}], "logs": [], "processID": "p2", "warnings": null}, {"traceID": "035db1fec5a771dd", "spanID": "b4262dd3377ddf14", "flags": 1, "operationName": "compose_creator_client", "references": [{"refType": "CHILD_OF", "traceID": "035db1fec5a771dd", "spanID": "de8f831afe09a226"}], "startTime": 1666132434488337, "duration": 172, "tags": [{"key": "internal.span.format", "type": "string", "value": "proto"}], "logs": [], "processID": "p2", "warnings": null}, {"traceID": "035db1fec5a771dd", "spanID": "c6597a8b8c0698f9", "flags": 1, "operationName": "compose_text_client", "references": [{"refType": "CHILD_OF", "traceID": "035db1fec5a771dd", "spanID": "de8f831afe09a226"}], "startTime": 1666132434487689, "duration": 1372, "tags": [{"key": "internal.span.format", "type": "string", "value": "proto"}], "logs": [], "processID": "p2", "warnings": null}, {"traceID": "035db1fec5a771dd", "spanID": "de8f831afe09a226", "flags": 1, "operationName": "compose_post_server", "references": [{"refType": "CHILD_OF", "traceID": "035db1fec5a771dd", "spanID": "407808e629578ce4"}], "startTime": 1666132434487443, "duration": 3713, "tags": [{"key": "internal.span.format", "type": "string", "value": "proto"}], "logs": [], "processID": "p2", "warnings": null}, {"traceID": "035db1fec5a771dd", "spanID": "a98c9f1ae6701a86", "flags": 1, "operationName": "store_post_client", "references": [{"refType": "CHILD_OF", "traceID": "035db1fec5a771dd", "spanID": "de8f831afe09a226"}], "startTime": 1666132434489163, "duration": 434, "tags": [{"key": "internal.span.format", "type": "string", "value": "proto"}], "logs": [], "processID": "p2", "warnings": null}, {"traceID": "035db1fec5a771dd", "spanID": "9fbf0c496dc81f86", "flags": 1, "operationName": "write_user_timeline_client", "references": [{"refType": "CHILD_OF", "traceID": "035db1fec5a771dd", "spanID": "de8f831afe09a226"}], "startTime": 1666132434489642, "duration": 686, "tags": [{"key": "internal.span.format", "type": "string", "value": "proto"}], "logs": [], "processID": "p2", "warnings": null}, {"traceID": "035db1fec5a771dd", "spanID": "f7281939cf834522", "flags": 1, "operationName": "compose_media_client", "references": [{"refType": "CHILD_OF", "traceID": "035db1fec5a771dd", "spanID": "de8f831afe09a226"}], "startTime": 1666132434488090, "duration": 159, "tags": [{"key": "internal.span.format", "type": "string", "value": "proto"}], "logs": [], "processID": "p2", "warnings": null}, {"traceID": "035db1fec5a771dd", "spanID": "c31826b7b010a056", "flags": 1, "operationName": "write_home_timeline_client", "references": [{"refType": "CHILD_OF", "traceID": "035db1fec5a771dd", "spanID": "de8f831afe09a226"}], "startTime": 1666132434490358, "duration": 789, "tags": [{"key": "internal.span.format", "type": "string", "value": "proto"}], "logs": [], "processID": "p2", "warnings": null}, {"traceID": "035db1fec5a771dd", "spanID": "bdd557bcab391285", "flags": 1, "operationName": "compose_user_mentions_memcached_get_client", "references": [{"refType": "CHILD_OF", "traceID": "035db1fec5a771dd", "spanID": "23fdf52937d7a598"}], "startTime": 1666132434488555, "duration": 268, "tags": [{"key": "internal.span.format", "type": "string", "value": "proto"}], "logs": [], "processID": "p3", "warnings": null}, {"traceID": "035db1fec5a771dd", "spanID": "23fdf52937d7a598", "flags": 1, "operationName": "compose_user_mentions_server", "references": [{"refType": "CHILD_OF", "traceID": "035db1fec5a771dd", "spanID": "54ad5e57b3643e5c"}], "startTime": 1666132434488544, "duration": 290, "tags": [{"key": "internal.span.format", "type": "string", "value": "proto"}], "logs": [], "processID": "p3", "warnings": null}, {"traceID": "035db1fec5a771dd", "spanID": "0ab88c3425f48dea", "flags": 1, "operationName": "compose_creator_server", "references": [{"refType": "CHILD_OF", "traceID": "035db1fec5a771dd", "spanID": "b4262dd3377ddf14"}], "startTime": 1666132434488417, "duration": 7, "tags": [{"key": "internal.span.format", "type": "string", "value": "proto"}], "logs": [], "processID": "p4", "warnings": null}, {"traceID": "035db1fec5a771dd", "spanID": "da5dd0091957bc15", "flags": 1, "operationName": "get_followers_client", "references": [{"refType": "CHILD_OF", "traceID": "035db1fec5a771dd", "spanID": "12f6c1db64e3a2a8"}], "startTime": 1666132434490437, "duration": 235, "tags": [{"key": "internal.span.format", "type": "string", "value": "proto"}], "logs": [], "processID": "p5", "warnings": null}, {"traceID": "035db1fec5a771dd", "spanID": "ecda475e897d8a26", "flags": 1, "operationName": "write_home_timeline_redis_update_client", "references": [{"refType": "CHILD_OF", "traceID": "035db1fec5a771dd", "spanID": "12f6c1db64e3a2a8"}], "startTime": 1666132434490688, "duration": 336, "tags": [{"key": "internal.span.format", "type": "string", "value": "proto"}], "logs": [], "processID": "p5", "warnings": null}, {"traceID": "035db1fec5a771dd", "spanID": "12f6c1db64e3a2a8", "flags": 1, "operationName": "write_home_timeline_server", "references": [{"refType": "CHILD_OF", "traceID": "035db1fec5a771dd", "spanID": "c31826b7b010a056"}], "startTime": 1666132434490434, "duration": 601, "tags": [{"key": "internal.span.format", "type": "string", "value": "proto"}], "logs": [], "processID": "p5", "warnings": null}, {"traceID": "035db1fec5a771dd", "spanID": "b1d9f6b320bcd42f", "flags": 1, "operationName": "post_storage_mongo_insert_client", "references": [{"refType": "CHILD_OF", "traceID": "035db1fec5a771dd", "spanID": "02246b2bfbbd7935"}], "startTime": 1666132434489276, "duration": 266, "tags": [{"key": "internal.span.format", "type": "string", "value": "proto"}], "logs": [], "processID": "p6", "warnings": null}, {"traceID": "035db1fec5a771dd", "spanID": "02246b2bfbbd7935", "flags": 1, "operationName": "store_post_server", "references": [{"refType": "CHILD_OF", "traceID": "035db1fec5a771dd", "spanID": "a98c9f1ae6701a86"}], "startTime": 1666132434489254, "duration": 303, "tags": [{"key": "internal.span.format", "type": "string", "value": "proto"}], "logs": [], "processID": "p6", "warnings": null}, {"traceID": "035db1fec5a771dd", "spanID": "035db1fec5a771dd", "flags": 1, "operationName": "/wrk2-api/post/compose", "references": [], "startTime": 1666132434487000, "duration": 4325, "tags": [{"key": "sampler.type", "type": "string", "value": "probabilistic"}, {"key": "sampler.param", "type": "float64", "value": 0.2}, {"key": "http.status_code", "type": "int64", "value": 200}, {"key": "http.status_line", "type": "string", "value": ""}, {"key": "component", "type": "string", "value": "nginx"}, {"key": "nginx.worker_pid", "type": "string", "value": "11"}, {"key": "peer.address", "type": "string", "value": "172.18.0.1:44890"}, {"key": "http.method", "type": "string", "value": "POST"}, {"key": "http.url", "type": "string", "value": "http://localhost:8080/wrk2-api/post/compose"}, {"key": "http.host", "type": "string", "value": "localhost:8080"}, {"key": "internal.span.format", "type": "string", "value": "proto"}], "logs": [], "processID": "p7", "warnings": null}, {"traceID": "035db1fec5a771dd", "spanID": "56b0c69c6869a8ae", "flags": 1, "operationName": "/wrk2-api/post/compose", "references": [{"refType": "CHILD_OF", "traceID": "035db1fec5a771dd", "spanID": "035db1fec5a771dd"}], "startTime": 1666132434487128, "duration": 4197, "tags": [{"key": "component", "type": "string", "value": "nginx"}, {"key": "nginx.worker_pid", "type": "string", "value": "11"}, {"key": "peer.address", "type": "string", "value": "172.18.0.1:44890"}, {"key": "http.method", "type": "string", "value": "POST"}, {"key": "http.url", "type": "string", "value": "http://localhost:8080/wrk2-api/post/compose"}, {"key": "http.host", "type": "string", "value": "localhost:8080"}, {"key": "http.status_code", "type": "int64", "value": 200}, {"key": "http.status_line", "type": "string", "value": ""}, {"key": "internal.span.format", "type": "string", "value": "proto"}], "logs": [], "processID": "p7", "warnings": null}, {"traceID": "035db1fec5a771dd", "spanID": "407808e629578ce4", "flags": 1, "operationName": "compose_post_client", "references": [{"refType": "CHILD_OF", "traceID": "035db1fec5a771dd", "spanID": "56b0c69c6869a8ae"}], "startTime": 1666132434487238, "duration": 4032, "tags": [{"key": "internal.span.format", "type": "string", "value": "proto"}], "logs": [], "processID": "p7", "warnings": null}, {"traceID": "035db1fec5a771dd", "spanID": "dedb9b6e4576251a", "flags": 1, "operationName": "write_user_timeline_mongo_insert_client", "references": [{"refType": "CHILD_OF", "traceID": "035db1fec5a771dd", "spanID": "18ff6b0dcf8f7ade"}], "startTime": 1666132434489719, "duration": 375, "tags": [{"key": "internal.span.format", "type": "string", "value": "proto"}], "logs": [], "processID": "p8", "warnings": null}, {"traceID": "035db1fec5a771dd", "spanID": "c399cf1c92ea74e1", "flags": 1, "operationName": "write_user_timeline_redis_update_client", "references": [{"refType": "CHILD_OF", "traceID": "035db1fec5a771dd", "spanID": "18ff6b0dcf8f7ade"}], "startTime": 1666132434490111, "duration": 171, "tags": [{"key": "internal.span.format", "type": "string", "value": "proto"}], "logs": [], "processID": "p8", "warnings": null}, {"traceID": "035db1fec5a771dd", "spanID": "18ff6b0dcf8f7ade", "flags": 1, "operationName": "write_user_timeline_server", "references": [{"refType": "CHILD_OF", "traceID": "035db1fec5a771dd", "spanID": "9fbf0c496dc81f86"}], "startTime": 1666132434489706, "duration": 584, "tags": [{"key": "internal.span.format", "type": "string", "value": "proto"}], "logs": [], "processID": "p8", "warnings": null}, {"traceID": "035db1fec5a771dd", "spanID": "834bf3ff30f3a76a", "flags": 1, "operationName": "compose_urls_client", "references": [{"refType": "CHILD_OF", "traceID": "035db1fec5a771dd", "spanID": "5c7db4111943c149"}], "startTime": 1666132434488346, "duration": 587, "tags": [{"key": "internal.span.format", "type": "string", "value": "proto"}], "logs": [], "processID": "p9", "warnings": null}, {"traceID": "035db1fec5a771dd", "spanID": "5c7db4111943c149", "flags": 1, "operationName": "compose_text_server", "references": [{"refType": "CHILD_OF", "traceID": "035db1fec5a771dd", "spanID": "c6597a8b8c0698f9"}], "startTime": 1666132434487778, "duration": 1234, "tags": [{"key": "internal.span.format", "type": "string", "value": "proto"}], "logs": [], "processID": "p9", "warnings": null}, {"traceID": "035db1fec5a771dd", "spanID": "54ad5e57b3643e5c", "flags": 1, "operationName": "compose_user_mentions_client", "references": [{"refType": "CHILD_OF", "traceID": "035db1fec5a771dd", "spanID": "5c7db4111943c149"}], "startTime": 1666132434488356, "duration": 586, "tags": [{"key": "internal.span.format", "type": "string", "value": "proto"}], "logs": [], "processID": "p9", "warnings": null}, {"traceID": "035db1fec5a771dd", "spanID": "c6bb76d4715086ff", "flags": 1, "operationName": "compose_media_server", "references": [{"refType": "CHILD_OF", "traceID": "035db1fec5a771dd", "spanID": "f7281939cf834522"}], "startTime": 1666132434488171, "duration": 8, "tags": [{"key": "internal.span.format", "type": "string", "value": "proto"}], "logs": [], "processID": "p10", "warnings": null}, {"traceID": "035db1fec5a771dd", "spanID": "c8da9984581cf60b", "flags": 1, "operationName": "get_followers_server", "references": [{"refType": "CHILD_OF", "traceID": "035db1fec5a771dd", "spanID": "da5dd0091957bc15"}], "startTime": 1666132434490507, "duration": 134, "tags": [{"key": "internal.span.format", "type": "string", "value": "proto"}], "logs": [], "processID": "p11", "warnings": null}, {"traceID": "035db1fec5a771dd", "spanID": "4bd2468b0d01af63", "flags": 1, "operationName": "social_graph_redis_get_client", "references": [{"refType": "CHILD_OF", "traceID": "035db1fec5a771dd", "spanID": "c8da9984581cf60b"}], "startTime": 1666132434490512, "duration": 119, "tags": [{"key": "internal.span.format", "type": "string", "value": "proto"}], "logs": [], "processID": "p11", "warnings": null}, {"traceID": "035db1fec5a771dd", "spanID": "d7c70ded38ddfb7b", "flags": 1, "operationName": "compose_unique_id_server", "references": [{"refType": "CHILD_OF", "traceID": "035db1fec5a771dd", "spanID": "f2cf15bccc746087"}], "startTime": 1666132434487776, "duration": 13, "tags": [{"key": "internal.span.format", "type": "string", "value": "proto"}], "logs": [], "processID": "p12", "warnings": null}], "processes": {"p1": {"serviceName": "url-shorten-service", "tags": [{"key": "hostname", "type": "string", "value": "url-shorten-service"}, {"key": "ip", "type": "string", "value": "127.0.0.1"}, {"key": "jaeger.version", "type": "string", "value": "C++-0.4.2"}]}, "p10": {"serviceName": "media-service", "tags": [{"key": "hostname", "type": "string", "value": "media-service"}, {"key": "ip", "type": "string", "value": "127.0.0.1"}, {"key": "jaeger.version", "type": "string", "value": "C++-0.4.2"}]}, "p11": {"serviceName": "social-graph-service", "tags": [{"key": "hostname", "type": "string", "value": "social-graph-service"}, {"key": "ip", "type": "string", "value": "127.0.0.1"}, {"key": "jaeger.version", "type": "string", "value": "C++-0.4.2"}]}, "p12": {"serviceName": "unique-id-service", "tags": [{"key": "hostname", "type": "string", "value": "unique-id-service"}, {"key": "ip", "type": "string", "value": "127.0.0.1"}, {"key": "jaeger.version", "type": "string", "value": "C++-0.4.2"}]}, "p2": {"serviceName": "compose-post-service", "tags": [{"key": "hostname", "type": "string", "value": "compose-post-service"}, {"key": "ip", "type": "string", "value": "127.0.0.1"}, {"key": "jaeger.version", "type": "string", "value": "C++-0.4.2"}]}, "p3": {"serviceName": "user-mention-service", "tags": [{"key": "hostname", "type": "string", "value": "user-mention-service"}, {"key": "ip", "type": "string", "value": "127.0.0.1"}, {"key": "jaeger.version", "type": "string", "value": "C++-0.4.2"}]}, "p4": {"serviceName": "user-service", "tags": [{"key": "hostname", "type": "string", "value": "user-service"}, {"key": "ip", "type": "string", "value": "127.0.0.1"}, {"key": "jaeger.version", "type": "string", "value": "C++-0.4.2"}]}, "p5": {"serviceName": "home-timeline-service", "tags": [{"key": "hostname", "type": "string", "value": "home-timeline-service"}, {"key": "ip", "type": "string", "value": "127.0.0.1"}, {"key": "jaeger.version", "type": "string", "value": "C++-0.4.2"}]}, "p6": {"serviceName": "post-storage-service", "tags": [{"key": "hostname", "type": "string", "value": "post-storage-service"}, {"key": "ip", "type": "string", "value": "127.0.0.1"}, {"key": "jaeger.version", "type": "string", "value": "C++-0.4.2"}]}, "p7": {"serviceName": "nginx-web-server", "tags": [{"key": "hostname", "type": "string", "value": "nginx-thrift"}, {"key": "ip", "type": "string", "value": "127.0.0.1"}, {"key": "jaeger.version", "type": "string", "value": "C++-0.4.2"}]}, "p8": {"serviceName": "user-timeline-service", "tags": [{"key": "hostname", "type": "string", "value": "user-timeline-service"}, {"key": "ip", "type": "string", "value": "127.0.0.1"}, {"key": "jaeger.version", "type": "string", "value": "C++-0.4.2"}]}, "p9": {"serviceName": "text-service", "tags": [{"key": "hostname", "type": "string", "value": "text-service"}, {"key": "ip", "type": "string", "value": "127.0.0.1"}, {"key": "jaeger.version", "type": "string", "value": "C++-0.4.2"}]}}, "warnings": null}