{"traceID": "102a803ada0f3026", "spans": [{"traceID": "102a803ada0f3026", "spanID": "ef812fac444af65a", "flags": 1, "operationName": "compose_media_client", "references": [{"refType": "CHILD_OF", "traceID": "102a803ada0f3026", "spanID": "dcb00a4a0321406c"}], "startTime": 1666132433280548, "duration": 129, "tags": [{"key": "internal.span.format", "type": "string", "value": "proto"}], "logs": [], "processID": "p1", "warnings": null}, {"traceID": "102a803ada0f3026", "spanID": "93eace9d1314fabd", "flags": 1, "operationName": "compose_creator_client", "references": [{"refType": "CHILD_OF", "traceID": "102a803ada0f3026", "spanID": "dcb00a4a0321406c"}], "startTime": 1666132433281104, "duration": 144, "tags": [{"key": "internal.span.format", "type": "string", "value": "proto"}], "logs": [], "processID": "p1", "warnings": null}, {"traceID": "102a803ada0f3026", "spanID": "0ab1e95268ee0ee1", "flags": 1, "operationName": "compose_text_client", "references": [{"refType": "CHILD_OF", "traceID": "102a803ada0f3026", "spanID": "dcb00a4a0321406c"}], "startTime": 1666132433280491, "duration": 1716, "tags": [{"key": "internal.span.format", "type": "string", "value": "proto"}], "logs": [], "processID": "p1", "warnings": null}, {"traceID": "102a803ada0f3026", "spanID": "b1a4016917e82400", "flags": 1, "operationName": "write_user_timeline_client", "references": [{"refType": "CHILD_OF", "traceID": "102a803ada0f3026", "spanID": "dcb00a4a0321406c"}], "startTime": 1666132433282791, "duration": 596, "tags": [{"key": "internal.span.format", "type": "string", "value": "proto"}], "logs": [], "processID": "p1", "warnings": null}, {"traceID": "102a803ada0f3026", "spanID": "50c3e3c9a4453b13", "flags": 1, "operationName": "write_home_timeline_client", "references": [{"refType": "CHILD_OF", "traceID": "102a803ada0f3026", "spanID": "dcb00a4a0321406c"}], "startTime": 1666132433283422, "duration": 1937, "tags": [{"key": "internal.span.format", "type": "string", "value": "proto"}], "logs": [], "processID": "p1", "warnings": null}, {"traceID": "102a803ada0f3026", "spanID": "dcb00a4a0321406c", "flags": 1, "operationName": "compose_post_server", "references": [{"refType": "CHILD_OF", "traceID": "102a803ada0f3026", "spanID": "852d9c0d3ad4adb3"}], "startTime": 1666132433280434, "duration": 4940, "tags": [{"key": "internal.span.format", "type": "string", "value": "proto"}], "logs": [], "processID": "p1", "warnings": null}, {"traceID": "102a803ada0f3026", "spanID": "e71ba46f6dac8d6b", "flags": 1, "operationName": "store_post_client", "references": [{"refType": "CHILD_OF", "traceID": "102a803ada0f3026", "spanID": "dcb00a4a0321406c"}], "startTime": 1666132433282309, "duration": 431, "tags": [{"key": "internal.span.format", "type": "string", "value": "proto"}], "logs": [], "processID": "p1", "warnings": null}, {"traceID": "102a803ada0f3026", "spanID": "d74fa2176136d9d0", "flags": 1, "operationName": "compose_unique_id_client", "references": [{"refType": "CHILD_OF", "traceID": "102a803ada0f3026", "spanID": "dcb00a4a0321406c"}], "startTime": 1666132433280656, "duration": 140, "tags": [{"key": "internal.span.format", "type": "string", "value": "proto"}], "logs": [], "processID": "p1", "warnings": null}, {"traceID": "102a803ada0f3026", "spanID": "91640b63703858b1", "flags": 1, "operationName": "compose_user_mentions_client", "references": [{"refType": "CHILD_OF", "traceID": "102a803ada0f3026", "spanID": "2cf8a7b75f46e59a"}], "startTime": 1666132433281036, "duration": 537, "tags": [{"key": "internal.span.format", "type": "string", "value": "proto"}], "logs": [], "processID": "p2", "warnings": null}, {"traceID": "102a803ada0f3026", "spanID": "58f7a08405a56121", "flags": 1, "operationName": "compose_urls_client", "references": [{"refType": "CHILD_OF", "traceID": "102a803ada0f3026", "spanID": "2cf8a7b75f46e59a"}], "startTime": 1666132433281021, "duration": 996, "tags": [{"key": "internal.span.format", "type": "string", "value": "proto"}], "logs": [], "processID": "p2", "warnings": null}, {"traceID": "102a803ada0f3026", "spanID": "2cf8a7b75f46e59a", "flags": 1, "operationName": "compose_text_server", "references": [{"refType": "CHILD_OF", "traceID": "102a803ada0f3026", "spanID": "0ab1e95268ee0ee1"}], "startTime": 1666132433280561, "duration": 1580, "tags": [{"key": "internal.span.format", "type": "string", "value": "proto"}], "logs": [], "processID": "p2", "warnings": null}, {"traceID": "102a803ada0f3026", "spanID": "54cd48fbf1132900", "flags": 1, "operationName": "compose_media_server", "references": [{"refType": "CHILD_OF", "traceID": "102a803ada0f3026", "spanID": "ef812fac444af65a"}], "startTime": 1666132433280615, "duration": 5, "tags": [{"key": "internal.span.format", "type": "string", "value": "proto"}], "logs": [], "processID": "p3", "warnings": null}, {"traceID": "102a803ada0f3026", "spanID": "2f21d84f83ed6a74", "flags": 1, "operationName": "write_user_timeline_mongo_insert_client", "references": [{"refType": "CHILD_OF", "traceID": "102a803ada0f3026", "spanID": "30150ab3e753608a"}], "startTime": 1666132433282873, "duration": 367, "tags": [{"key": "internal.span.format", "type": "string", "value": "proto"}], "logs": [], "processID": "p4", "warnings": null}, {"traceID": "102a803ada0f3026", "spanID": "8125d65d85da4418", "flags": 1, "operationName": "write_user_timeline_redis_update_client", "references": [{"refType": "CHILD_OF", "traceID": "102a803ada0f3026", "spanID": "30150ab3e753608a"}], "startTime": 1666132433283254, "duration": 80, "tags": [{"key": "internal.span.format", "type": "string", "value": "proto"}], "logs": [], "processID": "p4", "warnings": null}, {"traceID": "102a803ada0f3026", "spanID": "30150ab3e753608a", "flags": 1, "operationName": "write_user_timeline_server", "references": [{"refType": "CHILD_OF", "traceID": "102a803ada0f3026", "spanID": "b1a4016917e82400"}], "startTime": 1666132433282860, "duration": 482, "tags": [{"key": "internal.span.format", "type": "string", "value": "proto"}], "logs": [], "processID": "p4", "warnings": null}, {"traceID": "102a803ada0f3026", "spanID": "256ab723801c5a9b", "flags": 1, "operationName": "social_graph_redis_get_client", "references": [{"refType": "CHILD_OF", "traceID": "102a803ada0f3026", "spanID": "fb333e4b43a4932e"}], "startTime": 1666132433283563, "duration": 94, "tags": [{"key": "internal.span.format", "type": "string", "value": "proto"}], "logs": [], "processID": "p5", "warnings": null}, {"traceID": "102a803ada0f3026", "spanID": "fb333e4b43a4932e", "flags": 1, "operationName": "get_followers_server", "references": [{"refType": "CHILD_OF", "traceID": "102a803ada0f3026", "spanID": "a0549192de7c7e79"}], "startTime": 1666132433283555, "duration": 116, "tags": [{"key": "internal.span.format", "type": "string", "value": "proto"}], "logs": [], "processID": "p5", "warnings": null}, {"traceID": "102a803ada0f3026", "spanID": "2d85779e70495643", "flags": 1, "operationName": "url_mongo_insert_client", "references": [{"refType": "CHILD_OF", "traceID": "102a803ada0f3026", "spanID": "7c7f317ae44ec4c0"}], "startTime": 1666132433281577, "duration": 332, "tags": [{"key": "internal.span.format", "type": "string", "value": "proto"}], "logs": [], "processID": "p6", "warnings": null}, {"traceID": "102a803ada0f3026", "spanID": "7c7f317ae44ec4c0", "flags": 1, "operationName": "compose_urls_server", "references": [{"refType": "CHILD_OF", "traceID": "102a803ada0f3026", "spanID": "58f7a08405a56121"}], "startTime": 1666132433281120, "duration": 827, "tags": [{"key": "internal.span.format", "type": "string", "value": "proto"}], "logs": [], "processID": "p6", "warnings": null}, {"traceID": "102a803ada0f3026", "spanID": "a0549192de7c7e79", "flags": 1, "operationName": "get_followers_client", "references": [{"refType": "CHILD_OF", "traceID": "102a803ada0f3026", "spanID": "6ac557bd161645a1"}], "startTime": 1666132433283493, "duration": 223, "tags": [{"key": "internal.span.format", "type": "string", "value": "proto"}], "logs": [], "processID": "p7", "warnings": null}, {"traceID": "102a803ada0f3026", "spanID": "b1152fa269206ad2", "flags": 1, "operationName": "write_home_timeline_redis_update_client", "references": [{"refType": "CHILD_OF", "traceID": "102a803ada0f3026", "spanID": "6ac557bd161645a1"}], "startTime": 1666132433283730, "duration": 1518, "tags": [{"key": "internal.span.format", "type": "string", "value": "proto"}], "logs": [], "processID": "p7", "warnings": null}, {"traceID": "102a803ada0f3026", "spanID": "6ac557bd161645a1", "flags": 1, "operationName": "write_home_timeline_server", "references": [{"refType": "CHILD_OF", "traceID": "102a803ada0f3026", "spanID": "50c3e3c9a4453b13"}], "startTime": 1666132433283491, "duration": 1772, "tags": [{"key": "internal.span.format", "type": "string", "value": "proto"}], "logs": [], "processID": "p7", "warnings": null}, {"traceID": "102a803ada0f3026", "spanID": "a3f2a0d6b0ec2207", "flags": 1, "operationName": "compose_user_mentions_memcached_get_client", "references": [{"refType": "CHILD_OF", "traceID": "102a803ada0f3026", "spanID": "562aa6b2983dabe5"}], "startTime": 1666132433281130, "duration": 281, "tags": [{"key": "internal.span.format", "type": "string", "value": "proto"}], "logs": [], "processID": "p8", "warnings": null}, {"traceID": "102a803ada0f3026", "spanID": "562aa6b2983dabe5", "flags": 1, "operationName": "compose_user_mentions_server", "references": [{"refType": "CHILD_OF", "traceID": "102a803ada0f3026", "spanID": "91640b63703858b1"}], "startTime": 1666132433281118, "duration": 304, "tags": [{"key": "internal.span.format", "type": "string", "value": "proto"}], "logs": [], "processID": "p8", "warnings": null}, {"traceID": "102a803ada0f3026", "spanID": "51f46800384eaea7", "flags": 1, "operationName": "post_storage_mongo_insert_client", "references": [{"refType": "CHILD_OF", "traceID": "102a803ada0f3026", "spanID": "c2eb52b3b60ddf83"}], "startTime": 1666132433282415, "duration": 267, "tags": [{"key": "internal.span.format", "type": "string", "value": "proto"}], "logs": [], "processID": "p9", "warnings": null}, {"traceID": "102a803ada0f3026", "spanID": "c2eb52b3b60ddf83", "flags": 1, "operationName": "store_post_server", "references": [{"refType": "CHILD_OF", "traceID": "102a803ada0f3026", "spanID": "e71ba46f6dac8d6b"}], "startTime": 1666132433282396, "duration": 296, "tags": [{"key": "internal.span.format", "type": "string", "value": "proto"}], "logs": [], "processID": "p9", "warnings": null}, {"traceID": "102a803ada0f3026", "spanID": "5ff2e0a570e704b2", "flags": 1, "operationName": "compose_unique_id_server", "references": [{"refType": "CHILD_OF", "traceID": "102a803ada0f3026", "spanID": "d74fa2176136d9d0"}], "startTime": 1666132433280726, "duration": 13, "tags": [{"key": "internal.span.format", "type": "string", "value": "proto"}], "logs": [], "processID": "p10", "warnings": null}, {"traceID": "102a803ada0f3026", "spanID": "17e106fe3132ab03", "flags": 1, "operationName": "compose_creator_server", "references": [{"refType": "CHILD_OF", "traceID": "102a803ada0f3026", "spanID": "93eace9d1314fabd"}], "startTime": 1666132433281177, "duration": 7, "tags": [{"key": "internal.span.format", "type": "string", "value": "proto"}], "logs": [], "processID": "p11", "warnings": null}, {"traceID": "102a803ada0f3026", "spanID": "852d9c0d3ad4adb3", "flags": 1, "operationName": "compose_post_client", "references": [{"refType": "CHILD_OF", "traceID": "102a803ada0f3026", "spanID": "9df5858bd63a88fa"}], "startTime": 1666132433280282, "duration": 5214, "tags": [{"key": "internal.span.format", "type": "string", "value": "proto"}], "logs": [], "processID": "p12", "warnings": null}, {"traceID": "102a803ada0f3026", "spanID": "9df5858bd63a88fa", "flags": 1, "operationName": "/wrk2-api/post/compose", "references": [{"refType": "CHILD_OF", "traceID": "102a803ada0f3026", "spanID": "102a803ada0f3026"}], "startTime": 1666132433280189, "duration": 5352, "tags": [{"key": "component", "type": "string", "value": "nginx"}, {"key": "nginx.worker_pid", "type": "string", "value": "7"}, {"key": "peer.address", "type": "string", "value": "172.18.0.1:45300"}, {"key": "http.method", "type": "string", "value": "POST"}, {"key": "http.url", "type": "string", "value": "http://localhost:8080/wrk2-api/post/compose"}, {"key": "http.host", "type": "string", "value": "localhost:8080"}, {"key": "http.status_code", "type": "int64", "value": 200}, {"key": "http.status_line", "type": "string", "value": ""}, {"key": "internal.span.format", "type": "string", "value": "proto"}], "logs": [], "processID": "p12", "warnings": null}, {"traceID": "102a803ada0f3026", "spanID": "102a803ada0f3026", "flags": 1, "operationName": "/wrk2-api/post/compose", "references": [], "startTime": 1666132433280000, "duration": 5541, "tags": [{"key": "sampler.type", "type": "string", "value": "probabilistic"}, {"key": "sampler.param", "type": "float64", "value": 0.2}, {"key": "http.status_code", "type": "int64", "value": 200}, {"key": "http.status_line", "type": "string", "value": ""}, {"key": "component", "type": "string", "value": "nginx"}, {"key": "nginx.worker_pid", "type": "string", "value": "7"}, {"key": "peer.address", "type": "string", "value": "172.18.0.1:45300"}, {"key": "http.method", "type": "string", "value": "POST"}, {"key": "http.url", "type": "string", "value": "http://localhost:8080/wrk2-api/post/compose"}, {"key": "http.host", "type": "string", "value": "localhost:8080"}, {"key": "internal.span.format", "type": "string", "value": "proto"}], "logs": [], "processID": "p12", "warnings": null}], "processes": {"p1": {"serviceName": "compose-post-service", "tags": [{"key": "hostname", "type": "string", "value": "compose-post-service"}, {"key": "ip", "type": "string", "value": "127.0.0.1"}, {"key": "jaeger.version", "type": "string", "value": "C++-0.4.2"}]}, "p10": {"serviceName": "unique-id-service", "tags": [{"key": "hostname", "type": "string", "value": "unique-id-service"}, {"key": "ip", "type": "string", "value": "127.0.0.1"}, {"key": "jaeger.version", "type": "string", "value": "C++-0.4.2"}]}, "p11": {"serviceName": "user-service", "tags": [{"key": "hostname", "type": "string", "value": "user-service"}, {"key": "ip", "type": "string", "value": "127.0.0.1"}, {"key": "jaeger.version", "type": "string", "value": "C++-0.4.2"}]}, "p12": {"serviceName": "nginx-web-server", "tags": [{"key": "hostname", "type": "string", "value": "nginx-thrift"}, {"key": "ip", "type": "string", "value": "127.0.0.1"}, {"key": "jaeger.version", "type": "string", "value": "C++-0.4.2"}]}, "p2": {"serviceName": "text-service", "tags": [{"key": "hostname", "type": "string", "value": "text-service"}, {"key": "ip", "type": "string", "value": "127.0.0.1"}, {"key": "jaeger.version", "type": "string", "value": "C++-0.4.2"}]}, "p3": {"serviceName": "media-service", "tags": [{"key": "hostname", "type": "string", "value": "media-service"}, {"key": "ip", "type": "string", "value": "127.0.0.1"}, {"key": "jaeger.version", "type": "string", "value": "C++-0.4.2"}]}, "p4": {"serviceName": "user-timeline-service", "tags": [{"key": "hostname", "type": "string", "value": "user-timeline-service"}, {"key": "ip", "type": "string", "value": "127.0.0.1"}, {"key": "jaeger.version", "type": "string", "value": "C++-0.4.2"}]}, "p5": {"serviceName": "social-graph-service", "tags": [{"key": "hostname", "type": "string", "value": "social-graph-service"}, {"key": "ip", "type": "string", "value": "127.0.0.1"}, {"key": "jaeger.version", "type": "string", "value": "C++-0.4.2"}]}, "p6": {"serviceName": "url-shorten-service", "tags": [{"key": "hostname", "type": "string", "value": "url-shorten-service"}, {"key": "ip", "type": "string", "value": "127.0.0.1"}, {"key": "jaeger.version", "type": "string", "value": "C++-0.4.2"}]}, "p7": {"serviceName": "home-timeline-service", "tags": [{"key": "hostname", "type": "string", "value": "home-timeline-service"}, {"key": "ip", "type": "string", "value": "127.0.0.1"}, {"key": "jaeger.version", "type": "string", "value": "C++-0.4.2"}]}, "p8": {"serviceName": "user-mention-service", "tags": [{"key": "hostname", "type": "string", "value": "user-mention-service"}, {"key": "ip", "type": "string", "value": "127.0.0.1"}, {"key": "jaeger.version", "type": "string", "value": "C++-0.4.2"}]}, "p9": {"serviceName": "post-storage-service", "tags": [{"key": "hostname", "type": "string", "value": "post-storage-service"}, {"key": "ip", "type": "string", "value": "127.0.0.1"}, {"key": "jaeger.version", "type": "string", "value": "C++-0.4.2"}]}}, "warnings": null}