{"traceID": "1b91a489b1996e6c", "spans": [{"traceID": "1b91a489b1996e6c", "spanID": "af11f664c5916948", "flags": 1, "operationName": "social_graph_redis_update_client", "references": [{"refType": "CHILD_OF", "traceID": "1b91a489b1996e6c", "spanID": "ae6e0c56bc970c01"}], "startTime": 1666132391881138, "duration": 174, "tags": [{"key": "internal.span.format", "type": "string", "value": "proto"}], "logs": [], "processID": "p1", "warnings": null}, {"traceID": "1b91a489b1996e6c", "spanID": "5dc90717153bdfb8", "flags": 1, "operationName": "social_graph_mongo_update_client", "references": [{"refType": "CHILD_OF", "traceID": "1b91a489b1996e6c", "spanID": "ae6e0c56bc970c01"}], "startTime": 1666132391881054, "duration": 629, "tags": [{"key": "internal.span.format", "type": "string", "value": "proto"}], "logs": [], "processID": "p1", "warnings": null}, {"traceID": "1b91a489b1996e6c", "spanID": "cb3808f56229101e", "flags": 1, "operationName": "mongo_update_client", "references": [{"refType": "CHILD_OF", "traceID": "1b91a489b1996e6c", "spanID": "ae6e0c56bc970c01"}], "startTime": 1666132391881087, "duration": 604, "tags": [{"key": "internal.span.format", "type": "string", "value": "proto"}], "logs": [], "processID": "p1", "warnings": null}, {"traceID": "1b91a489b1996e6c", "spanID": "ae6e0c56bc970c01", "flags": 1, "operationName": "follow_server", "references": [{"refType": "CHILD_OF", "traceID": "1b91a489b1996e6c", "spanID": "770447d010f30844"}], "startTime": 1666132391878190, "duration": 6459, "tags": [{"key": "internal.span.format", "type": "string", "value": "proto"}], "logs": [], "processID": "p1", "warnings": null}, {"traceID": "1b91a489b1996e6c", "spanID": "770447d010f30844", "flags": 1, "operationName": "follow_with_username_server", "references": [{"refType": "CHILD_OF", "traceID": "1b91a489b1996e6c", "spanID": "eef2ea8d41983e0a"}], "startTime": 1666132391863304, "duration": 21351, "tags": [{"key": "internal.span.format", "type": "string", "value": "proto"}], "logs": [], "processID": "p1", "warnings": null}, {"traceID": "1b91a489b1996e6c", "spanID": "c33735f91702e170", "flags": 1, "operationName": "get_user_id_server", "references": [{"refType": "CHILD_OF", "traceID": "1b91a489b1996e6c", "spanID": "770447d010f30844"}], "startTime": 1666132391874301, "duration": 124, "tags": [{"key": "internal.span.format", "type": "string", "value": "proto"}], "logs": [], "processID": "p2", "warnings": null}, {"traceID": "1b91a489b1996e6c", "spanID": "0b8dd4222db18686", "flags": 1, "operationName": "get_user_id_server", "references": [{"refType": "CHILD_OF", "traceID": "1b91a489b1996e6c", "spanID": "770447d010f30844"}], "startTime": 1666132391874664, "duration": 146, "tags": [{"key": "internal.span.format", "type": "string", "value": "proto"}], "logs": [], "processID": "p2", "warnings": null}, {"traceID": "1b91a489b1996e6c", "spanID": "b30b812b98be83af", "flags": 1, "operationName": "user_mmc_get_user_id_client", "references": [{"refType": "CHILD_OF", "traceID": "1b91a489b1996e6c", "spanID": "0b8dd4222db18686"}], "startTime": 1666132391874675, "duration": 121, "tags": [{"key": "internal.span.format", "type": "string", "value": "proto"}], "logs": [], "processID": "p2", "warnings": null}, {"traceID": "1b91a489b1996e6c", "spanID": "29fc87fe5562fa37", "flags": 1, "operationName": "user_mmc_get_user_id_client", "references": [{"refType": "CHILD_OF", "traceID": "1b91a489b1996e6c", "spanID": "c33735f91702e170"}], "startTime": 1666132391874310, "duration": 100, "tags": [{"key": "internal.span.format", "type": "string", "value": "proto"}], "logs": [], "processID": "p2", "warnings": null}, {"traceID": "1b91a489b1996e6c", "spanID": "1b91a489b1996e6c", "flags": 1, "operationName": "/wrk2-api/user/follow", "references": [], "startTime": 1666132391862000, "duration": 22745, "tags": [{"key": "sampler.type", "type": "string", "value": "probabilistic"}, {"key": "sampler.param", "type": "float64", "value": 0.2}, {"key": "http.status_code", "type": "int64", "value": 200}, {"key": "http.status_line", "type": "string", "value": ""}, {"key": "component", "type": "string", "value": "nginx"}, {"key": "nginx.worker_pid", "type": "string", "value": "8"}, {"key": "peer.address", "type": "string", "value": "172.18.0.1:42358"}, {"key": "http.method", "type": "string", "value": "POST"}, {"key": "http.url", "type": "string", "value": "http://127.0.0.1:8080/wrk2-api/user/follow"}, {"key": "http.host", "type": "string", "value": "127.0.0.1:8080"}, {"key": "internal.span.format", "type": "string", "value": "proto"}], "logs": [], "processID": "p3", "warnings": null}, {"traceID": "1b91a489b1996e6c", "spanID": "eef2ea8d41983e0a", "flags": 1, "operationName": "follow_client", "references": [{"refType": "CHILD_OF", "traceID": "1b91a489b1996e6c", "spanID": "38ffbd4d5a713c73"}], "startTime": 1666132391862497, "duration": 22209, "tags": [{"key": "internal.span.format", "type": "string", "value": "proto"}], "logs": [], "processID": "p3", "warnings": null}, {"traceID": "1b91a489b1996e6c", "spanID": "38ffbd4d5a713c73", "flags": 1, "operationName": "/wrk2-api/user/follow", "references": [{"refType": "CHILD_OF", "traceID": "1b91a489b1996e6c", "spanID": "1b91a489b1996e6c"}], "startTime": 1666132391862090, "duration": 22654, "tags": [{"key": "component", "type": "string", "value": "nginx"}, {"key": "nginx.worker_pid", "type": "string", "value": "8"}, {"key": "peer.address", "type": "string", "value": "172.18.0.1:42358"}, {"key": "http.method", "type": "string", "value": "POST"}, {"key": "http.url", "type": "string", "value": "http://127.0.0.1:8080/wrk2-api/user/follow"}, {"key": "http.host", "type": "string", "value": "127.0.0.1:8080"}, {"key": "http.status_code", "type": "int64", "value": 200}, {"key": "http.status_line", "type": "string", "value": ""}, {"key": "internal.span.format", "type": "string", "value": "proto"}], "logs": [], "processID": "p3", "warnings": null}], "processes": {"p1": {"serviceName": "social-graph-service", "tags": [{"key": "hostname", "type": "string", "value": "social-graph-service"}, {"key": "ip", "type": "string", "value": "127.0.0.1"}, {"key": "jaeger.version", "type": "string", "value": "C++-0.4.2"}]}, "p2": {"serviceName": "user-service", "tags": [{"key": "hostname", "type": "string", "value": "user-service"}, {"key": "ip", "type": "string", "value": "127.0.0.1"}, {"key": "jaeger.version", "type": "string", "value": "C++-0.4.2"}]}, "p3": {"serviceName": "nginx-web-server", "tags": [{"key": "hostname", "type": "string", "value": "nginx-thrift"}, {"key": "ip", "type": "string", "value": "127.0.0.1"}, {"key": "jaeger.version", "type": "string", "value": "C++-0.4.2"}]}}, "warnings": null}