{"traceID": "2c14ef4648320005", "spans": [{"traceID": "2c14ef4648320005", "spanID": "647c1b25f11be825", "flags": 1, "operationName": "post_storage_mmc_mget_client", "references": [{"refType": "CHILD_OF", "traceID": "2c14ef4648320005", "spanID": "28a36b876cca3a42"}], "startTime": 1667341238589223, "duration": 1103, "tags": [{"key": "internal.span.format", "type": "string", "value": "proto"}], "logs": [], "processID": "p1", "warnings": null}, {"traceID": "2c14ef4648320005", "spanID": "829ddcfae69a8d34", "flags": 1, "operationName": "mongo_find_client", "references": [{"refType": "CHILD_OF", "traceID": "2c14ef4648320005", "spanID": "28a36b876cca3a42"}], "startTime": 1667341238590489, "duration": 3657, "tags": [{"key": "internal.span.format", "type": "string", "value": "proto"}], "logs": [], "processID": "p1", "warnings": null}, {"traceID": "2c14ef4648320005", "spanID": "727bca7959c21c82", "flags": 1, "operationName": "mmc_set_client", "references": [{"refType": "CHILD_OF", "traceID": "2c14ef4648320005", "spanID": "28a36b876cca3a42"}], "startTime": 1667341238597244, "duration": 1049, "tags": [{"key": "internal.span.format", "type": "string", "value": "proto"}], "logs": [], "processID": "p1", "warnings": null}, {"traceID": "2c14ef4648320005", "spanID": "28a36b876cca3a42", "flags": 1, "operationName": "post_storage_read_posts_server", "references": [{"refType": "CHILD_OF", "traceID": "2c14ef4648320005", "spanID": "f897834a2e022caf"}], "startTime": 1667341238589146, "duration": 9226, "tags": [{"key": "internal.span.format", "type": "string", "value": "proto"}], "logs": [], "processID": "p1", "warnings": null}, {"traceID": "2c14ef4648320005", "spanID": "d6cb08916fd525c4", "flags": 1, "operationName": "ReadUserTimeline", "references": [{"refType": "CHILD_OF", "traceID": "2c14ef4648320005", "spanID": "039d32793d99e7ea"}], "startTime": 1667341238585331, "duration": 29123, "tags": [{"key": "internal.span.format", "type": "string", "value": "proto"}], "logs": [], "processID": "p2", "warnings": null}, {"traceID": "2c14ef4648320005", "spanID": "039d32793d99e7ea", "flags": 1, "operationName": "/wrk2-api/user-timeline/read", "references": [{"refType": "CHILD_OF", "traceID": "2c14ef4648320005", "spanID": "2c14ef4648320005"}], "startTime": 1667341238585266, "duration": 29262, "tags": [{"key": "component", "type": "string", "value": "nginx"}, {"key": "nginx.worker_pid", "type": "string", "value": "20"}, {"key": "peer.address", "type": "string", "value": "172.18.0.1:53224"}, {"key": "http.method", "type": "string", "value": "GET"}, {"key": "http.url", "type": "string", "value": "http://localhost:8080/wrk2-api/user-timeline/read?user_id=353&start=57&stop=67"}, {"key": "http.host", "type": "string", "value": "localhost:8080"}, {"key": "http.status_code", "type": "int64", "value": 200}, {"key": "http.status_line", "type": "string", "value": ""}, {"key": "internal.span.format", "type": "string", "value": "proto"}], "logs": [], "processID": "p2", "warnings": null}, {"traceID": "2c14ef4648320005", "spanID": "2c14ef4648320005", "flags": 1, "operationName": "/wrk2-api/user-timeline/read", "references": [], "startTime": 1667341238577000, "duration": 37528, "tags": [{"key": "sampler.type", "type": "string", "value": "probabilistic"}, {"key": "sampler.param", "type": "float64", "value": 0.2}, {"key": "http.status_code", "type": "int64", "value": 200}, {"key": "http.status_line", "type": "string", "value": ""}, {"key": "component", "type": "string", "value": "nginx"}, {"key": "nginx.worker_pid", "type": "string", "value": "20"}, {"key": "peer.address", "type": "string", "value": "172.18.0.1:53224"}, {"key": "http.method", "type": "string", "value": "GET"}, {"key": "http.url", "type": "string", "value": "http://localhost:8080/wrk2-api/user-timeline/read?user_id=353&start=57&stop=67"}, {"key": "http.host", "type": "string", "value": "localhost:8080"}, {"key": "internal.span.format", "type": "string", "value": "proto"}], "logs": [], "processID": "p2", "warnings": null}, {"traceID": "2c14ef4648320005", "spanID": "25c649cb1a42310b", "flags": 1, "operationName": "read_user_timeline_redis_find_client", "references": [{"refType": "CHILD_OF", "traceID": "2c14ef4648320005", "spanID": "f897834a2e022caf"}], "startTime": 1667341238587673, "duration": 492, "tags": [{"key": "internal.span.format", "type": "string", "value": "proto"}], "logs": [], "processID": "p3", "warnings": null}, {"traceID": "2c14ef4648320005", "spanID": "f897834a2e022caf", "flags": 1, "operationName": "read_user_timeline_server", "references": [{"refType": "CHILD_OF", "traceID": "2c14ef4648320005", "spanID": "d6cb08916fd525c4"}], "startTime": 1667341238587665, "duration": 11446, "tags": [{"key": "internal.span.format", "type": "string", "value": "proto"}], "logs": [], "processID": "p3", "warnings": null}], "processes": {"p1": {"serviceName": "post-storage-service", "tags": [{"key": "hostname", "type": "string", "value": "post-storage-service"}, {"key": "ip", "type": "string", "value": "127.0.0.1"}, {"key": "jaeger.version", "type": "string", "value": "C++-0.4.2"}]}, "p2": {"serviceName": "nginx-web-server", "tags": [{"key": "hostname", "type": "string", "value": "nginx-thrift"}, {"key": "ip", "type": "string", "value": "127.0.0.1"}, {"key": "jaeger.version", "type": "string", "value": "C++-0.4.2"}]}, "p3": {"serviceName": "user-timeline-service", "tags": [{"key": "hostname", "type": "string", "value": "user-timeline-service"}, {"key": "ip", "type": "string", "value": "127.0.0.1"}, {"key": "jaeger.version", "type": "string", "value": "C++-0.4.2"}]}}, "warnings": null}