{"traceID": "0d90ff1171eebc76", "spans": [{"traceID": "0d90ff1171eebc76", "spanID": "0a998640dfdd60d1", "flags": 1, "operationName": "compose_media_client", "references": [{"refType": "CHILD_OF", "traceID": "0d90ff1171eebc76", "spanID": "ab2385dd2dd38870"}], "startTime": 1666132437392759, "duration": 163, "tags": [{"key": "internal.span.format", "type": "string", "value": "proto"}], "logs": [], "processID": "p1", "warnings": null}, {"traceID": "0d90ff1171eebc76", "spanID": "63d747d88ebe5561", "flags": 1, "operationName": "compose_unique_id_client", "references": [{"refType": "CHILD_OF", "traceID": "0d90ff1171eebc76", "spanID": "ab2385dd2dd38870"}], "startTime": 1666132437392786, "duration": 148, "tags": [{"key": "internal.span.format", "type": "string", "value": "proto"}], "logs": [], "processID": "p1", "warnings": null}, {"traceID": "0d90ff1171eebc76", "spanID": "93206fd1e88eaa46", "flags": 1, "operationName": "compose_creator_client", "references": [{"refType": "CHILD_OF", "traceID": "0d90ff1171eebc76", "spanID": "ab2385dd2dd38870"}], "startTime": 1666132437392956, "duration": 137, "tags": [{"key": "internal.span.format", "type": "string", "value": "proto"}], "logs": [], "processID": "p1", "warnings": null}, {"traceID": "0d90ff1171eebc76", "spanID": "f6975ac19da41058", "flags": 1, "operationName": "compose_text_client", "references": [{"refType": "CHILD_OF", "traceID": "0d90ff1171eebc76", "spanID": "ab2385dd2dd38870"}], "startTime": 1666132437393137, "duration": 3291, "tags": [{"key": "internal.span.format", "type": "string", "value": "proto"}], "logs": [], "processID": "p1", "warnings": null}, {"traceID": "0d90ff1171eebc76", "spanID": "4e883fd3cac55d53", "flags": 1, "operationName": "store_post_client", "references": [{"refType": "CHILD_OF", "traceID": "0d90ff1171eebc76", "spanID": "ab2385dd2dd38870"}], "startTime": 1666132437396653, "duration": 768, "tags": [{"key": "internal.span.format", "type": "string", "value": "proto"}], "logs": [], "processID": "p1", "warnings": null}, {"traceID": "0d90ff1171eebc76", "spanID": "98e87c86d69e7b39", "flags": 1, "operationName": "write_user_timeline_client", "references": [{"refType": "CHILD_OF", "traceID": "0d90ff1171eebc76", "spanID": "ab2385dd2dd38870"}], "startTime": 1666132437397488, "duration": 782, "tags": [{"key": "internal.span.format", "type": "string", "value": "proto"}], "logs": [], "processID": "p1", "warnings": null}, {"traceID": "0d90ff1171eebc76", "spanID": "d392d5a0f9981286", "flags": 1, "operationName": "write_home_timeline_client", "references": [{"refType": "CHILD_OF", "traceID": "0d90ff1171eebc76", "spanID": "ab2385dd2dd38870"}], "startTime": 1666132437398291, "duration": 1435, "tags": [{"key": "internal.span.format", "type": "string", "value": "proto"}], "logs": [], "processID": "p1", "warnings": null}, {"traceID": "0d90ff1171eebc76", "spanID": "ab2385dd2dd38870", "flags": 1, "operationName": "compose_post_server", "references": [{"refType": "CHILD_OF", "traceID": "0d90ff1171eebc76", "spanID": "65992a8fd937e5bf"}], "startTime": 1666132437392636, "duration": 7103, "tags": [{"key": "internal.span.format", "type": "string", "value": "proto"}], "logs": [], "processID": "p1", "warnings": null}, {"traceID": "0d90ff1171eebc76", "spanID": "62adb89c843d45a2", "flags": 1, "operationName": "compose_urls_client", "references": [{"refType": "CHILD_OF", "traceID": "0d90ff1171eebc76", "spanID": "61551803031590bf"}], "startTime": 1666132437393710, "duration": 2463, "tags": [{"key": "internal.span.format", "type": "string", "value": "proto"}], "logs": [], "processID": "p2", "warnings": null}, {"traceID": "0d90ff1171eebc76", "spanID": "b4476af1176a19d8", "flags": 1, "operationName": "compose_user_mentions_client", "references": [{"refType": "CHILD_OF", "traceID": "0d90ff1171eebc76", "spanID": "61551803031590bf"}], "startTime": 1666132437393777, "duration": 2489, "tags": [{"key": "internal.span.format", "type": "string", "value": "proto"}], "logs": [], "processID": "p2", "warnings": null}, {"traceID": "0d90ff1171eebc76", "spanID": "61551803031590bf", "flags": 1, "operationName": "compose_text_server", "references": [{"refType": "CHILD_OF", "traceID": "0d90ff1171eebc76", "spanID": "f6975ac19da41058"}], "startTime": 1666132437393230, "duration": 3139, "tags": [{"key": "internal.span.format", "type": "string", "value": "proto"}], "logs": [], "processID": "p2", "warnings": null}, {"traceID": "0d90ff1171eebc76", "spanID": "5a33749e1e1ba9fe", "flags": 1, "operationName": "write_user_timeline_redis_update_client", "references": [{"refType": "CHILD_OF", "traceID": "0d90ff1171eebc76", "spanID": "dd5271abb7f8cef9"}], "startTime": 1666132437398055, "duration": 110, "tags": [{"key": "internal.span.format", "type": "string", "value": "proto"}], "logs": [], "processID": "p3", "warnings": null}, {"traceID": "0d90ff1171eebc76", "spanID": "13b6254403d2c155", "flags": 1, "operationName": "write_user_timeline_mongo_insert_client", "references": [{"refType": "CHILD_OF", "traceID": "0d90ff1171eebc76", "spanID": "dd5271abb7f8cef9"}], "startTime": 1666132437397639, "duration": 399, "tags": [{"key": "internal.span.format", "type": "string", "value": "proto"}], "logs": [], "processID": "p3", "warnings": null}, {"traceID": "0d90ff1171eebc76", "spanID": "dd5271abb7f8cef9", "flags": 1, "operationName": "write_user_timeline_server", "references": [{"refType": "CHILD_OF", "traceID": "0d90ff1171eebc76", "spanID": "98e87c86d69e7b39"}], "startTime": 1666132437397622, "duration": 550, "tags": [{"key": "internal.span.format", "type": "string", "value": "proto"}], "logs": [], "processID": "p3", "warnings": null}, {"traceID": "0d90ff1171eebc76", "spanID": "8af01362bae8e2fb", "flags": 1, "operationName": "get_followers_client", "references": [{"refType": "CHILD_OF", "traceID": "0d90ff1171eebc76", "spanID": "2fda2b79f2c15ad1"}], "startTime": 1666132437398354, "duration": 192, "tags": [{"key": "internal.span.format", "type": "string", "value": "proto"}], "logs": [], "processID": "p4", "warnings": null}, {"traceID": "0d90ff1171eebc76", "spanID": "47484395ab7e1bfd", "flags": 1, "operationName": "write_home_timeline_redis_update_client", "references": [{"refType": "CHILD_OF", "traceID": "0d90ff1171eebc76", "spanID": "2fda2b79f2c15ad1"}], "startTime": 1666132437398560, "duration": 1113, "tags": [{"key": "internal.span.format", "type": "string", "value": "proto"}], "logs": [], "processID": "p4", "warnings": null}, {"traceID": "0d90ff1171eebc76", "spanID": "2fda2b79f2c15ad1", "flags": 1, "operationName": "write_home_timeline_server", "references": [{"refType": "CHILD_OF", "traceID": "0d90ff1171eebc76", "spanID": "d392d5a0f9981286"}], "startTime": 1666132437398351, "duration": 1334, "tags": [{"key": "internal.span.format", "type": "string", "value": "proto"}], "logs": [], "processID": "p4", "warnings": null}, {"traceID": "0d90ff1171eebc76", "spanID": "5f79d01e3c2d8b4b", "flags": 1, "operationName": "url_mongo_insert_client", "references": [{"refType": "CHILD_OF", "traceID": "0d90ff1171eebc76", "spanID": "4815f7aef13f98a1"}], "startTime": 1666132437393861, "duration": 270, "tags": [{"key": "internal.span.format", "type": "string", "value": "proto"}], "logs": [], "processID": "p5", "warnings": null}, {"traceID": "0d90ff1171eebc76", "spanID": "4815f7aef13f98a1", "flags": 1, "operationName": "compose_urls_server", "references": [{"refType": "CHILD_OF", "traceID": "0d90ff1171eebc76", "spanID": "62adb89c843d45a2"}], "startTime": 1666132437393805, "duration": 356, "tags": [{"key": "internal.span.format", "type": "string", "value": "proto"}], "logs": [], "processID": "p5", "warnings": null}, {"traceID": "0d90ff1171eebc76", "spanID": "3d04dab3e4247b2a", "flags": 1, "operationName": "post_storage_mongo_insert_client", "references": [{"refType": "CHILD_OF", "traceID": "0d90ff1171eebc76", "spanID": "f232f8d8c8e1f580"}], "startTime": 1666132437396764, "duration": 598, "tags": [{"key": "internal.span.format", "type": "string", "value": "proto"}], "logs": [], "processID": "p6", "warnings": null}, {"traceID": "0d90ff1171eebc76", "spanID": "f232f8d8c8e1f580", "flags": 1, "operationName": "store_post_server", "references": [{"refType": "CHILD_OF", "traceID": "0d90ff1171eebc76", "spanID": "4e883fd3cac55d53"}], "startTime": 1666132437396745, "duration": 625, "tags": [{"key": "internal.span.format", "type": "string", "value": "proto"}], "logs": [], "processID": "p6", "warnings": null}, {"traceID": "0d90ff1171eebc76", "spanID": "83fa01e64da7f48b", "flags": 1, "operationName": "compose_creator_server", "references": [{"refType": "CHILD_OF", "traceID": "0d90ff1171eebc76", "spanID": "93206fd1e88eaa46"}], "startTime": 1666132437393030, "duration": 7, "tags": [{"key": "internal.span.format", "type": "string", "value": "proto"}], "logs": [], "processID": "p7", "warnings": null}, {"traceID": "0d90ff1171eebc76", "spanID": "736b7251e043414c", "flags": 1, "operationName": "compose_user_mentions_memcached_get_client", "references": [{"refType": "CHILD_OF", "traceID": "0d90ff1171eebc76", "spanID": "a6cacdb0845aca2f"}], "startTime": 1666132437393864, "duration": 328, "tags": [{"key": "internal.span.format", "type": "string", "value": "proto"}], "logs": [], "processID": "p8", "warnings": null}, {"traceID": "0d90ff1171eebc76", "spanID": "a6cacdb0845aca2f", "flags": 1, "operationName": "compose_user_mentions_server", "references": [{"refType": "CHILD_OF", "traceID": "0d90ff1171eebc76", "spanID": "b4476af1176a19d8"}], "startTime": 1666132437393853, "duration": 352, "tags": [{"key": "internal.span.format", "type": "string", "value": "proto"}], "logs": [], "processID": "p8", "warnings": null}, {"traceID": "0d90ff1171eebc76", "spanID": "43e13156dc3c84a6", "flags": 1, "operationName": "compose_unique_id_server", "references": [{"refType": "CHILD_OF", "traceID": "0d90ff1171eebc76", "spanID": "63d747d88ebe5561"}], "startTime": 1666132437392860, "duration": 13, "tags": [{"key": "internal.span.format", "type": "string", "value": "proto"}], "logs": [], "processID": "p9", "warnings": null}, {"traceID": "0d90ff1171eebc76", "spanID": "1f8fbd3387c0067b", "flags": 1, "operationName": "social_graph_redis_get_client", "references": [{"refType": "CHILD_OF", "traceID": "0d90ff1171eebc76", "spanID": "5799915ee2cb4d08"}], "startTime": 1666132437398416, "duration": 86, "tags": [{"key": "internal.span.format", "type": "string", "value": "proto"}], "logs": [], "processID": "p10", "warnings": null}, {"traceID": "0d90ff1171eebc76", "spanID": "5799915ee2cb4d08", "flags": 1, "operationName": "get_followers_server", "references": [{"refType": "CHILD_OF", "traceID": "0d90ff1171eebc76", "spanID": "8af01362bae8e2fb"}], "startTime": 1666132437398411, "duration": 96, "tags": [{"key": "internal.span.format", "type": "string", "value": "proto"}], "logs": [], "processID": "p10", "warnings": null}, {"traceID": "0d90ff1171eebc76", "spanID": "3f172962e1212e3d", "flags": 1, "operationName": "compose_media_server", "references": [{"refType": "CHILD_OF", "traceID": "0d90ff1171eebc76", "spanID": "0a998640dfdd60d1"}], "startTime": 1666132437392842, "duration": 9, "tags": [{"key": "internal.span.format", "type": "string", "value": "proto"}], "logs": [], "processID": "p11", "warnings": null}, {"traceID": "0d90ff1171eebc76", "spanID": "8effc2ced4284aac", "flags": 1, "operationName": "/wrk2-api/post/compose", "references": [{"refType": "CHILD_OF", "traceID": "0d90ff1171eebc76", "spanID": "0d90ff1171eebc76"}], "startTime": 1666132437392341, "duration": 7790, "tags": [{"key": "component", "type": "string", "value": "nginx"}, {"key": "nginx.worker_pid", "type": "string", "value": "30"}, {"key": "peer.address", "type": "string", "value": "172.18.0.1:45528"}, {"key": "http.method", "type": "string", "value": "POST"}, {"key": "http.url", "type": "string", "value": "http://localhost:8080/wrk2-api/post/compose"}, {"key": "http.host", "type": "string", "value": "localhost:8080"}, {"key": "http.status_code", "type": "int64", "value": 200}, {"key": "http.status_line", "type": "string", "value": ""}, {"key": "internal.span.format", "type": "string", "value": "proto"}], "logs": [], "processID": "p12", "warnings": null}, {"traceID": "0d90ff1171eebc76", "spanID": "0d90ff1171eebc76", "flags": 1, "operationName": "/wrk2-api/post/compose", "references": [], "startTime": 1666132437392000, "duration": 8131, "tags": [{"key": "sampler.type", "type": "string", "value": "probabilistic"}, {"key": "sampler.param", "type": "float64", "value": 0.2}, {"key": "http.status_code", "type": "int64", "value": 200}, {"key": "http.status_line", "type": "string", "value": ""}, {"key": "component", "type": "string", "value": "nginx"}, {"key": "nginx.worker_pid", "type": "string", "value": "30"}, {"key": "peer.address", "type": "string", "value": "172.18.0.1:45528"}, {"key": "http.method", "type": "string", "value": "POST"}, {"key": "http.url", "type": "string", "value": "http://localhost:8080/wrk2-api/post/compose"}, {"key": "http.host", "type": "string", "value": "localhost:8080"}, {"key": "internal.span.format", "type": "string", "value": "proto"}], "logs": [], "processID": "p12", "warnings": null}, {"traceID": "0d90ff1171eebc76", "spanID": "65992a8fd937e5bf", "flags": 1, "operationName": "compose_post_client", "references": [{"refType": "CHILD_OF", "traceID": "0d90ff1171eebc76", "spanID": "8effc2ced4284aac"}], "startTime": 1666132437392427, "duration": 7674, "tags": [{"key": "internal.span.format", "type": "string", "value": "proto"}], "logs": [], "processID": "p12", "warnings": null}], "processes": {"p1": {"serviceName": "compose-post-service", "tags": [{"key": "hostname", "type": "string", "value": "compose-post-service"}, {"key": "ip", "type": "string", "value": "127.0.0.1"}, {"key": "jaeger.version", "type": "string", "value": "C++-0.4.2"}]}, "p10": {"serviceName": "social-graph-service", "tags": [{"key": "hostname", "type": "string", "value": "social-graph-service"}, {"key": "ip", "type": "string", "value": "127.0.0.1"}, {"key": "jaeger.version", "type": "string", "value": "C++-0.4.2"}]}, "p11": {"serviceName": "media-service", "tags": [{"key": "hostname", "type": "string", "value": "media-service"}, {"key": "ip", "type": "string", "value": "127.0.0.1"}, {"key": "jaeger.version", "type": "string", "value": "C++-0.4.2"}]}, "p12": {"serviceName": "nginx-web-server", "tags": [{"key": "hostname", "type": "string", "value": "nginx-thrift"}, {"key": "ip", "type": "string", "value": "127.0.0.1"}, {"key": "jaeger.version", "type": "string", "value": "C++-0.4.2"}]}, "p2": {"serviceName": "text-service", "tags": [{"key": "hostname", "type": "string", "value": "text-service"}, {"key": "ip", "type": "string", "value": "127.0.0.1"}, {"key": "jaeger.version", "type": "string", "value": "C++-0.4.2"}]}, "p3": {"serviceName": "user-timeline-service", "tags": [{"key": "hostname", "type": "string", "value": "user-timeline-service"}, {"key": "ip", "type": "string", "value": "127.0.0.1"}, {"key": "jaeger.version", "type": "string", "value": "C++-0.4.2"}]}, "p4": {"serviceName": "home-timeline-service", "tags": [{"key": "hostname", "type": "string", "value": "home-timeline-service"}, {"key": "ip", "type": "string", "value": "127.0.0.1"}, {"key": "jaeger.version", "type": "string", "value": "C++-0.4.2"}]}, "p5": {"serviceName": "url-shorten-service", "tags": [{"key": "hostname", "type": "string", "value": "url-shorten-service"}, {"key": "ip", "type": "string", "value": "127.0.0.1"}, {"key": "jaeger.version", "type": "string", "value": "C++-0.4.2"}]}, "p6": {"serviceName": "post-storage-service", "tags": [{"key": "hostname", "type": "string", "value": "post-storage-service"}, {"key": "ip", "type": "string", "value": "127.0.0.1"}, {"key": "jaeger.version", "type": "string", "value": "C++-0.4.2"}]}, "p7": {"serviceName": "user-service", "tags": [{"key": "hostname", "type": "string", "value": "user-service"}, {"key": "ip", "type": "string", "value": "127.0.0.1"}, {"key": "jaeger.version", "type": "string", "value": "C++-0.4.2"}]}, "p8": {"serviceName": "user-mention-service", "tags": [{"key": "hostname", "type": "string", "value": "user-mention-service"}, {"key": "ip", "type": "string", "value": "127.0.0.1"}, {"key": "jaeger.version", "type": "string", "value": "C++-0.4.2"}]}, "p9": {"serviceName": "unique-id-service", "tags": [{"key": "hostname", "type": "string", "value": "unique-id-service"}, {"key": "ip", "type": "string", "value": "127.0.0.1"}, {"key": "jaeger.version", "type": "string", "value": "C++-0.4.2"}]}}, "warnings": null}